subete/__init__.py
subete/imghdr.py
subete/repo.py
subete-0.21.0.dist-info/LICENSE
subete-0.21.0.dist-info/METADATA
subete-0.21.0.dist-info/WHEEL
subete-0.21.0.dist-info/RECORD
